{
  "Static": {
    "txt2img_sampling": "DPM++ 2M",
    "txt2img_scheduler": "Karras",
    "txt2img_steps": 32,
    "txt2img_width": 768,
    "txt2img_height": 1024,
    "txt2img_batch_count": 1,
    "txt2img_batch_size": 1,
    "txt2img_hr-checkbox": false,
    "txt2img_hr_scale": 2,
    "txt2img_hr_upscaler": "4x-UltraMix_Smooth",
    "txt2img_hires_steps": 16,
    "txt2img_denoising_strength": 0.5,
    "txt2img_cfg_scale": 4,
    "txt2img_enable-checkbox": true,
    "txt2img_switch_at": 0.5
  }
}
